prompttest/__init__.py
prompttest/cli.py
prompttest/discovery.py
prompttest/llm.py
prompttest/models.py
prompttest/reporting.py
prompttest/runner.py
prompttest/templates/_customer_service.txt
prompttest/templates/_env.txt
prompttest/templates/_global_config.yml
prompttest/templates/_guide.md
prompttest/templates/_test_customers.yml
prompttest/ui.py
prompttest-0.2.2.dist-info/WHEEL
prompttest-0.2.2.dist-info/entry_points.txt
prompttest-0.2.2.dist-info/METADATA
prompttest-0.2.2.dist-info/RECORD
