Metadata-Version: 2.3
Name: prompttest
Version: 0.2.2
Summary: pytest for LLMs
Keywords: llm,ai,testing,pytest,prompt,automation,pypi
Author: Decoding Chris
Author-email: Decoding Chris <decodingchris@gmail.com>
License: MIT License
Classifier: License :: OSI Approved :: MIT License
Classifier: Programming Language :: Python :: 3
Classifier: Programming Language :: Python :: 3.11
Classifier: Programming Language :: Python :: 3.12
Classifier: Programming Language :: Python :: 3.13
Classifier: Operating System :: OS Independent
Classifier: Intended Audience :: Developers
Classifier: Topic :: Software Development :: Testing
Classifier: Topic :: Scientific/Engineering :: Artificial Intelligence
Requires-Dist: anyio>=4.10.0
Requires-Dist: httpx>=0.28.1
Requires-Dist: openai>=1.99.9
Requires-Dist: pydantic>=2.11.7
Requires-Dist: python-dotenv>=1.1.1
Requires-Dist: pyyaml>=6.0.2
Requires-Dist: rich>=14.1.0
Requires-Dist: typer>=0.16.0
Requires-Python: >=3.11
Project-URL: Repository, https://github.com/decodingchris/prompttest
